pyuser_agent/__init__.py
pyuser_agent/store_dump.json
pyuser_agent/utility.py
pyuser_agent-0.1.0.data/data/store_dump.json
pyuser_agent-0.1.0.dist-info/LICENSE
pyuser_agent-0.1.0.dist-info/METADATA
pyuser_agent-0.1.0.dist-info/WHEEL
pyuser_agent-0.1.0.dist-info/top_level.txt
pyuser_agent-0.1.0.dist-info/zip-safe
pyuser_agent-0.1.0.dist-info/RECORD
