Metadata-Version: 2.1
Name: pyuser_agent
Version: 0.1.0
Summary: The User-Agent request header is a characteristic string that lets servers and network peers identify the application, operating system, vendor, and/or version of the requesting user agent.
Home-page: UNKNOWN
Author: T.THAVASI
Author-email: ganeshanthavasigti1032000@gmail.com
License: MIT
Project-URL: Source, https://github.com/THAVASIGTI/pyuser_agent.git
Project-URL: Tracker, https://github.com/THAVASIGTI/pyuser_agent/issues
Platform: UNKNOWN
Classifier: Development Status :: 5 - Production/Stable
Classifier: Environment :: Console
Classifier: Environment :: Web Environment
Classifier: Intended Audience :: Developers
Classifier: Intended Audience :: System Administrators
Classifier: License :: OSI Approved :: MIT License
Classifier: Operating System :: OS Independent
Classifier: Programming Language :: Python :: 3
Classifier: Programming Language :: Python :: 3.5
Classifier: Programming Language :: Python :: 3.6
Classifier: Programming Language :: Python :: 3.7
Classifier: Programming Language :: Python :: 3.8
Classifier: Topic :: System
Classifier: Topic :: System :: Filesystems
Classifier: Topic :: Utilities
Requires-Python: >=3
License-File: LICENSE
